

{
  "personas": [
    {
      "id": "custodian",
      "label": "Data Custodian",
      "description": "Owns the dataset governance and release obligations.",
      "allowedSteps": [1, 2, 3, 4, 5],
      "allowedAppendices": [1, 2, 3, 4, 5, 6, 8, 9, 10, 11],
      "defaultLanding": "/steps/1"
    },
    {
      "id": "requestor",
      "label": "Data Requestor",
      "description": "Seeks access to synthetic data for a stated purpose.",
      "allowedSteps": [1, 2, 3, 5],
      "allowedAppendices": [1, 2, 3, 4, 6, 8, 10],
      "defaultLanding": "/steps/1"
    },
    {
      "id": "scientist",
      "label": "Data Scientist",
      "description": "Designs generation/utility/validation of synthetic data.",
      "allowedSteps": [1, 2, 3, 4, 5],
      "allowedAppendices": [1, 2, 3, 4, 5, 6, 8, 10, 11],
      "defaultLanding": "/steps/1"
    }
  ]
}
